ProxyTunneller
