Metadata-Version: 1.2
Name: ProxyTunneller
Version: 0.3.14
Summary: Library for create proxy tunnels
Home-page: https://github.com/Seven45/ProxyTunneller
Author: Dubrovin Semyon
Author-email: seven45@mail.ru
License: UNKNOWN
Platform: UNKNOWN
Requires-Python: >=3.7
